{
  "main": {
    "id": "53aba7fc378d21a6",
    "type": "split",
    "children": [
      {
        "id": "78e4a0b15b7748f0",
        "type": "tabs",
        "children": [
          {
            "id": "bf23ab12ab84277a",
            "type": "leaf",
            "state": {
              "type": "markdown",
              "state": {
                "file": "INU 컴공 4-2/컴퓨터 구조/Day 7. Digital Components (2) - Register.md",
                "mode": "source",
                "backlinks": true,
                "source": false
              }
            }
          }
        ]
      }
    ],
    "direction": "vertical"
  },
  "left": {
    "id": "04c159f58235a0d2",
    "type": "split",
    "children": [
      {
        "id": "bc2c2675d6e66503",
        "type": "tabs",
        "children": [
          {
            "id": "74fb16be485e952d",
            "type": "leaf",
            "state": {
              "type": "file-explorer",
              "state": {
                "sortOrder": "byCreatedTimeReverse"
              }
            }
          },
          {
            "id": "5dd151ca152034f1",
            "type": "leaf",
            "state": {
              "type": "search",
              "state": {
                "query": "",
                "matchingCase": false,
                "explainSearch": false,
                "collapseAll": false,
                "extraContext": false,
                "sortOrder": "alphabetical"
              }
            }
          },
          {
            "id": "f51a49acf61fdcdb",
            "type": "leaf",
            "state": {
              "type": "bookmarks",
              "state": {}
            }
          }
        ]
      }
    ],
    "direction": "horizontal",
    "width": 215.00390243530273
  },
  "right": {
    "id": "f4643c8e16838745",
    "type": "split",
    "children": [
      {
        "id": "b579d268d94e42dd",
        "type": "tabs",
        "children": [
          {
            "id": "0b3cc956257de8ae",
            "type": "leaf",
            "state": {
              "type": "backlink",
              "state": {
                "file": "INU 컴공 4-2/컴퓨터 구조/Day 7. Digital Components (2) - Register.md",
                "collapseAll": false,
                "extraContext": false,
                "sortOrder": "alphabetical",
                "showSearch": false,
                "searchQuery": "",
                "backlinkCollapsed": false,
                "unlinkedCollapsed": true
              }
            }
          },
          {
            "id": "d92fe30f27bf6f2f",
            "type": "leaf",
            "state": {
              "type": "outgoing-link",
              "state": {
                "file": "INU 컴공 4-2/컴퓨터 구조/Day 7. Digital Components (2) - Register.md",
                "linksCollapsed": false,
                "unlinkedCollapsed": true
              }
            }
          },
          {
            "id": "7b7091f3d9f41aec",
            "type": "leaf",
            "state": {
              "type": "tag",
              "state": {
                "sortOrder": "frequency",
                "useHierarchy": true
              }
            }
          },
          {
            "id": "f1ccf34d4e7df4b1",
            "type": "leaf",
            "state": {
              "type": "outline",
              "state": {
                "file": "INU 컴공 4-2/컴퓨터 구조/Day 7. Digital Components (2) - Register.md"
              }
            }
          },
          {
            "id": "bce346bc1a24dfc3",
            "type": "leaf",
            "state": {
              "type": "calendar",
              "state": {}
            }
          },
          {
            "id": "399449266ac8e61b",
            "type": "leaf",
            "state": {
              "type": "advanced-tables-toolbar",
              "state": {}
            }
          }
        ],
        "currentTab": 5
      }
    ],
    "direction": "horizontal",
    "width": 284,
    "collapsed": true
  },
  "left-ribbon": {
    "hiddenItems": {
      "switcher:Open quick switcher": false,
      "graph:Open graph view": false,
      "canvas:Create new canvas": false,
      "daily-notes:Open today's daily note": false,
      "templates:Insert template": false,
      "command-palette:Open command palette": false,
      "table-editor-obsidian:Advanced Tables Toolbar": false,
      "templater-obsidian:Templater": false
    }
  },
  "active": "bf23ab12ab84277a",
  "lastOpenFiles": [
    "INU 컴공 4-2/모바일 소프트웨어/Day 10. (Kotlin) Class.md",
    "INU 컴공 4-2/모바일 소프트웨어/Day 3. 첫번째 Application.md",
    "INU 컴공 4-2/Linux System/Day 4. VI Editor.md",
    "INU 컴공 4-2/Algorithm/Day 5. 분포에 의한 정렬.md",
    "INU 컴공 4-2/Algorithm/Day 4. 퀵 정렬 (중간 시험) & 합병 정렬 & 히프 정렬.md",
    "INU 컴공 4-2/Algorithm/Day 3. 성능 분석.md",
    "INU 컴공 4-2/Algorithm/Day 2. 에라토스테네스의 체, 두 수의 합, 파스칼의 수 삼각형, 최장 연속 순차.md",
    "INU 컴공 4-2/Algorithm/Algorithm.md",
    "INU 컴공 4-2/Linux System/Day 2. Linux 개요.md",
    "README.md",
    "INU 컴공 4-2/컴퓨터 비젼/Day 4(Off-line)..md",
    "INU 컴공 4-2/컴퓨터 비젼/Day 1. Computer Vision Introduction.md",
    "INU 컴공 4-2/INU 컴공 4-2.md",
    "conflict-files-obsidian-git.md",
    "gitignore.md",
    "INU 컴공 4-2/Linux System/Day 11. Shell Script Programming.md",
    "INU 컴공 4-2/Linux System/Day 10. 공간 할당, 쿼터의 개념.md",
    "INU 컴공 4-2/Linux System/Day 9. 디스크 관리 기본.md",
    "INU 컴공 4-2/모바일 소프트웨어/Day 13. (Android) Layout & Events.md",
    "Images/스크린샷 2023-10-12 오후 6.43.25.png",
    "Images/스크린샷 2023-10-12 오후 6.39.08.png",
    "Images/스크린샷 2023-10-12 오후 6.34.13.png",
    "Images/스크린샷 2023-10-12 오후 6.33.55.png",
    "Images/스크린샷 2023-10-12 오후 6.33.17.png",
    "Images/스크린샷 2023-10-12 오후 6.29.06.png",
    "Images/스크린샷 2023-10-12 오후 6.26.22.png",
    "Images/스크린샷 2023-10-12 오후 6.25.41.png",
    "Images/스크린샷 2023-10-12 오후 6.23.39.png",
    "Images/스크린샷 2023-10-12 오후 6.16.52.png",
    "INU 컴공 4-2/컴퓨터 구조/Day 8. Data Representation.md",
    "INU 컴공 4-2/컴퓨터 구조/Day 5. Sequential Circuits (순차 회로).md",
    "INU 컴공 4-2/컴퓨터 구조/Day 6. Digital Components - Decoder, Encoder, Multiplexer.md",
    "INU 컴공 4-2/컴퓨터 구조/Day 7. Digital Components (2) - Register.md",
    "INU 컴공 4-2/컴퓨터 구조/Day 4. 무관 조건, Combinational Circuit(조합회로), Flip-Flop, Sequential Circuit.md",
    "INU 컴공 4-2/컴퓨터 구조/Day 2. Map Simplification.md",
    "INU 컴공 4-2/컴퓨터 구조/Day 3. Map Simplification.md",
    "Templates",
    "INU 컴공 4-2/Linux System/Untitled",
    "INU 컴공 4-2/모바일 소프트웨어/Assignment",
    "INU 컴공 4-2/컴퓨터 구조/Untitled",
    "INU 컴공 4-2/C++/Lecture",
    "INU 컴공 4-2/C++/Q&A",
    "INU 컴공 4-2/C++/Assignments",
    "INU 컴공 4-2/C++/kotlin(1)-overview.pdf",
    "INU 컴공 4-2/C++/kotlin(2)-basic.pdf",
    "INU 컴공 4-2/Algorithm/Assignments"
  ]
}